{
  "flags": {},
  "shapes": [
    {
      "label": "Tree",
      "line_color": null,
      "fill_color": null,
      "points": [
        [
          212,
          143
        ],
        [
          236,
          137
        ],
        [
          249,
          144
        ],
        [
          284,
          128
        ],
        [
          283,
          113
        ],
        [
          273,
          107
        ],
        [
          284,
          94
        ],
        [
          288,
          91
        ],
        [
          288,
          80
        ],
        [
          281,
          71
        ],
        [
          271,
          82
        ],
        [
          267,
          70
        ],
        [
          260,
          62
        ],
        [
          268,
          50
        ],
        [
          261,
          42
        ],
        [
          263,
          32
        ],
        [
          252,
          23
        ],
        [
          253,
          9
        ],
        [
          223,
          2
        ],
        [
          199,
          13
        ],
        [
          198,
          31
        ],
        [
          205,
          38
        ],
        [
          201,
          51
        ],
        [
          208,
          65
        ],
        [
          188,
          75
        ],
        [
          174,
          91
        ],
        [
          193,
          103
        ],
        [
          181,
          116
        ],
        [
          185,
          130
        ],
        [
          194,
          141
        ]
      ]
    },
    {
      "label": "Tree",
      "line_color": null,
      "fill_color": null,
      "points": [
        [
          185,
          288
        ],
        [
          186,
          296
        ],
        [
          219,
          302
        ],
        [
          239,
          299
        ],
        [
          259,
          283
        ],
        [
          270,
          276
        ],
        [
          298,
          276
        ],
        [
          322,
          246
        ],
        [
          320,
          226
        ],
        [
          311,
          201
        ],
        [
          318,
          179
        ],
        [
          302,
          152
        ],
        [
          263,
          156
        ],
        [
          253,
          184
        ],
        [
          247,
          201
        ],
        [
          236,
          206
        ],
        [
          214,
          224
        ],
        [
          209,
          219
        ],
        [
          190,
          230
        ],
        [
          193,
          250
        ],
        [
          182,
          262
        ],
        [
          179,
          279
        ]
      ]
    },
    {
      "label": "Tree",
      "line_color": null,
      "fill_color": null,
      "points": [
        [
          119,
          542
        ],
        [
          131,
          551
        ],
        [
          148,
          548
        ],
        [
          167,
          551
        ],
        [
          180,
          559
        ],
        [
          198,
          562
        ],
        [
          226,
          539
        ],
        [
          232,
          528
        ],
        [
          266,
          497
        ],
        [
          280,
          502
        ],
        [
          297,
          492
        ],
        [
          297,
          462
        ],
        [
          298,
          453
        ],
        [
          284,
          451
        ],
        [
          273,
          439
        ],
        [
          283,
          425
        ],
        [
          272,
          393
        ],
        [
          250,
          390
        ],
        [
          236,
          395
        ],
        [
          230,
          384
        ],
        [
          217,
          392
        ],
        [
          191,
          380
        ],
        [
          170,
          385
        ],
        [
          158,
          378
        ],
        [
          125,
          401
        ],
        [
          120,
          407
        ],
        [
          120,
          433
        ],
        [
          109,
          461
        ],
        [
          119,
          495
        ]
      ]
    },
    {
      "label": "Tree",
      "line_color": null,
      "fill_color": null,
      "points": [
        [
          420,
          458
        ],
        [
          452,
          470
        ],
        [
          472,
          490
        ],
        [
          472,
          505
        ],
        [
          492,
          508
        ],
        [
          514,
          492
        ],
        [
          531,
          491
        ],
        [
          563,
          502
        ],
        [
          583,
          496
        ],
        [
          603,
          480
        ],
        [
          630,
          439
        ],
        [
          625,
          409
        ],
        [
          595,
          378
        ],
        [
          575,
          380
        ],
        [
          552,
          355
        ],
        [
          553,
          338
        ],
        [
          528,
          295
        ],
        [
          493,
          318
        ],
        [
          456,
          321
        ],
        [
          440,
          337
        ],
        [
          403,
          371
        ],
        [
          393,
          390
        ]
      ]
    },
    {
      "label": "Tree",
      "line_color": null,
      "fill_color": null,
      "points": [
        [
          594,
          356
        ],
        [
          604,
          374
        ],
        [
          626,
          400
        ],
        [
          697,
          423
        ],
        [
          717,
          407
        ],
        [
          735,
          387
        ],
        [
          732,
          364
        ],
        [
          712,
          342
        ],
        [
          729,
          319
        ],
        [
          739,
          286
        ],
        [
          705,
          246
        ],
        [
          684,
          232
        ],
        [
          668,
          239
        ],
        [
          657,
          225
        ],
        [
          636,
          240
        ],
        [
          613,
          240
        ],
        [
          572,
          278
        ]
      ]
    },
    {
      "label": "Tree",
      "line_color": null,
      "fill_color": null,
      "points": [
        [
          611,
          143
        ],
        [
          615,
          161
        ],
        [
          618,
          177
        ],
        [
          631,
          188
        ],
        [
          651,
          200
        ],
        [
          675,
          207
        ],
        [
          707,
          230
        ],
        [
          732,
          224
        ],
        [
          736,
          207
        ],
        [
          754,
          196
        ],
        [
          759,
          179
        ],
        [
          753,
          169
        ],
        [
          769,
          136
        ],
        [
          759,
          93
        ],
        [
          732,
          69
        ],
        [
          712,
          78
        ],
        [
          714,
          56
        ],
        [
          696,
          37
        ],
        [
          679,
          32
        ]
      ]
    },
    {
      "label": "Tree",
      "line_color": null,
      "fill_color": null,
      "points": [
        [
          298,
          73
        ],
        [
          358,
          42
        ],
        [
          416,
          78
        ],
        [
          414,
          119
        ],
        [
          391,
          123
        ],
        [
          362,
          148
        ],
        [
          304,
          131
        ]
      ]
    },
    {
      "label": "Tree",
      "line_color": null,
      "fill_color": null,
      "points": [
        [
          482,
          246
        ],
        [
          525,
          207
        ],
        [
          519,
          161
        ],
        [
          504,
          140
        ],
        [
          488,
          102
        ],
        [
          462,
          81
        ],
        [
          420,
          117
        ],
        [
          412,
          181
        ]
      ]
    },
    {
      "label": "Tree",
      "line_color": null,
      "fill_color": null,
      "points": [
        [
          336,
          233
        ],
        [
          395,
          237
        ],
        [
          418,
          205
        ],
        [
          383,
          148
        ],
        [
          329,
          166
        ]
      ]
    }
  ],
  "labels": [],
  "lineColor": [
    0,
    255,
    0,
    128
  ],
  "fillColor": [
    255,
    0,
    0,
    128
  ],
  "imagePath": "Area1.PNG",
  "imageData": null
}